{
    "data_1": [
        {
            "img_1": "1.png",
            "img_2": "heart.png",
            "img_3": "sale.png",
            "title": "Медный чайник с фарфоровой ручкой",
            "price": "1 953 грн"
        },
        {
            "img_1": "2.png",
            "img_2": "heart.png",
            "img_3": "sale.png",
            "title": "Медный чайник с фарфоровой ручкой",
            "price": "1 953 грн"
        },
        {
            "img_1": "3.png",
            "img_2": "heart.png",
            "img_3": "sale.png",
            "title": "Медный чайник с фарфоровой ручкой",
            "price": "1 953 грн"
        }
    ],
    "data_2": [
        {
            "img": "user.png",
            "icon": "union.png",
            "name": "Иван Иванов",
            "comment": "Наше оборудование прозводится вручную. Мы постоянно производим контроль качества произведенной продукции. В то же время, если в ходе транспортировки или эксплуатации в течении первых 2 лет происходят поломки, мы всегда находим с клиентом наиболее удобный вариант решения вопроса.",
            "date": "20.10.21"
        },
        {
            "img": "user.png",
            "icon": "union.png",
            "name": "Иван Иванов",
            "comment": "Наше оборудование прозводится вручную. Мы постоянно производим контроль качества произведенной продукции. В то же время, если в ходе транспортировки или эксплуатации в течении первых 2 лет происходят поломки, мы всегда находим с клиентом наиболее удобный вариант решения вопроса.",
            "date": "20.10.21"
        },
        {
            "img": "user.png",
            "icon": "union.png",
            "name": "Иван Иванов",
            "comment": "Наше оборудование прозводится вручную. Мы постоянно производим контроль качества произведенной продукции. В то же время, если в ходе транспортировки или эксплуатации в течении первых 2 лет происходят поломки, мы всегда находим с клиентом наиболее удобный вариант решения вопроса.",
            "date": "20.10.21"
        }
    ],

    "data_3": [
        {
            "img": "star.png",
            "title": "Изысканность",
            "descrip": "Наши изделия из меди являются очень практичными. В то же время они наполнят особой магией ваш дом или рабочее....",
            "more": "Читать больше"
        },
        {
            "img": "star.png",
            "title": "Изысканность",
            "descrip": "Наши изделия из меди являются очень практичными. В то же время они наполнят особой магией ваш дом или рабочее....",
            "more": "Читать больше"
        },
        {
            "img": "star.png",
            "title": "Изысканность",
            "descrip": "Наши изделия из меди являются очень практичными. В то же время они наполнят особой магией ваш дом или рабочее....",
            "more": "Читать больше"
        },
        {
            "img": "star.png",
            "title": "Изысканность",
            "descrip": "Наши изделия из меди являются очень практичными. В то же время они наполнят особой магией ваш дом или рабочее....",
            "more": "Читать больше"
        }
    ]
}